dbini_torch/__init__.py
dbini_torch/dbini.py
dbini_torch/solver.py
dbini_torch-1.0.2.dist-info/entry_points.txt
dbini_torch-1.0.2.dist-info/LICENSE
dbini_torch-1.0.2.dist-info/WHEEL
dbini_torch-1.0.2.dist-info/METADATA
dbini_torch-1.0.2.dist-info/RECORD
