Metadata-Version: 2.3
Name: dbini-torch
Version: 1.0.2
Summary: PyTorch optimized bilateral normal integration
Author-email: Sam Pepose <sampepose@gmail.com>
Requires-Python: >=3.10.1
Classifier: Development Status :: 5 - Production/Stable
Classifier: Intended Audience :: Developers
Classifier: License :: OSI Approved :: GNU General Public License v3 (GPLv3)
Classifier: Programming Language :: Python :: 3 :: Only
Classifier: Programming Language :: Python :: 3.10
Classifier: Programming Language :: Python :: 3.11
Classifier: Programming Language :: Python :: 3.12
Requires-Dist: torch
Requires-Dist: tqdm
Requires-Dist: flit >=3.2.0,<4.0.0 ; extra == "dev"
Requires-Dist: ruff ; extra == "dev"
Requires-Dist: bandit[toml] ; extra == "test"
Requires-Dist: check-manifest ; extra == "test"
Requires-Dist: pre-commit ; extra == "test"
Requires-Dist: pytest-cov ; extra == "test"
Requires-Dist: pytest-mock ; extra == "test"
Requires-Dist: pytest-runner ; extra == "test"
Requires-Dist: pytest ; extra == "test"
Requires-Dist: pytest-github-actions-annotate-failures ; extra == "test"
Requires-Dist: shellcheck-py ; extra == "test"
Requires-Dist: numpy ; extra == "test"
Requires-Dist: scipy ; extra == "test"
Requires-Dist: tqdm ; extra == "test"
Requires-Dist: opencv-python ; extra == "test"
Project-URL: Documentation, https://github.com/sampepose/dbini-torch/tree/main#readme
Project-URL: Issues, https://github.com/sampepose/dbini-torch/issues
Project-URL: Source, https://github.com/sampepose/dbini-torch
Provides-Extra: dev
Provides-Extra: test
